databutton_app_mcp/__init__.py
databutton_app_mcp/__main__.py
databutton_app_mcp-0.1.18.dist-info/METADATA
databutton_app_mcp-0.1.18.dist-info/WHEEL
databutton_app_mcp-0.1.18.dist-info/entry_points.txt
databutton_app_mcp-0.1.18.dist-info/licenses/LICENSE
databutton_app_mcp-0.1.18.dist-info/RECORD
