Metadata-Version: 2.4
Name: databutton-app-mcp
Version: 0.1.18
Summary: Call your Databutton app endpoints as LLM tools with MCP
Project-URL: Homepage, https://databutton.com
Project-URL: Repository, https://github.com/databutton/databutton-app-mcp
Project-URL: Documentation, https://docs.databutton.com
Project-URL: Support, https://databutton.com/support
Project-URL: Discord, https://discord.gg/K9aHvmmFtH
Author-email: Martin Sandve Alnæs <msa@databutton.io>
Maintainer-email: Martin Sandve Alnæs <msa@databutton.io>
License-Expression: MIT
License-File: LICENSE
Keywords: app,databutton,llm,mcp,tool
Classifier: Development Status :: 3 - Alpha
Classifier: Programming Language :: Python :: 3
Classifier: Programming Language :: Python :: 3.11
Classifier: Programming Language :: Python :: 3.12
Classifier: Programming Language :: Python :: 3.13
Requires-Python: >=3.11
Requires-Dist: certifi>=2025.1.31
Requires-Dist: httpx>=0.28.1
Requires-Dist: websockets>=15.0.1
